compas_cgal/_measure.cpython-310-darwin.so
compas_cgal/measure.py
compas_cgal/_intersections.cpython-310-darwin.so
compas_cgal/_subdivision.cpython-310-darwin.so
compas_cgal/reconstruction.py
compas_cgal/_booleans.cpython-310-darwin.so
compas_cgal/booleans.py
compas_cgal/__init__.py
compas_cgal/straight_skeleton_2.py
compas_cgal/_meshing.cpython-310-darwin.so
compas_cgal/types.py
compas_cgal/_triangulation.cpython-310-darwin.so
compas_cgal/subdivision.py
compas_cgal/intersections.py
compas_cgal/_reconstruction.cpython-310-darwin.so
compas_cgal/_straight_skeleton_2.cpython-310-darwin.so
compas_cgal/_types_std.cpython-310-darwin.so
compas_cgal/_skeletonization.cpython-310-darwin.so
compas_cgal/slicer.py
compas_cgal/meshing.py
compas_cgal/triangulation.py
compas_cgal/_slicer.cpython-310-darwin.so
compas_cgal/skeletonization.py
compas_cgal-0.9.1.dist-info/RECORD
compas_cgal-0.9.1.dist-info/WHEEL
compas_cgal-0.9.1.dist-info/METADATA
compas_cgal-0.9.1.dist-info/licenses/LICENSE
