Metadata-Version: 2.1
Name: compas_cgal
Version: 0.9.1
Summary: CGAL wrapper for COMPAS.
Author-Email: tom van mele <tom.v.mele@gmail.com>, Petras Vestartas <petrasvestartas@gmail.com>
Classifier: License :: OSI Approved :: GNU Lesser General Public License v3 (LGPLv3)
Project-URL: Homepage, https://github.com/compas-dev/compas_cgal
Requires-Python: >=3.9
